{
    "swagger": "2.0",
    "info": {
        "description": "A Fast Food ordering service API in Go using Gin framework.",
        "title": "Fast Food API",
        "termsOfService": "http://swagger.io/terms/",
        "contact": {
            "name": "API Support",
            "url": "http://www.swagger.io/support",
            "email": "support@swagger.io"
        },
        "license": {
            "name": "Apache 2.0",
            "url": "http://www.apache.org/licenses/LICENSE-2.0.html"
        },
        "version": "1.0"
    },
    "host": "localhost:8080",
    "basePath": "/",
    "paths": {
        "/categories": {
            "get": {
                "security": [
                    {
                        "BearerAuth": []
                    }
                ],
                "description": "Get list of all food categories",
                "produces": [
                    "application/json"
                ],
                "tags": [
                    "categories"
                ],
                "summary": "Get all categories",
                "responses": {
                    "200": {
                        "description": "OK",
                        "schema": {
                            "type": "array",
                            "items": {
                                "$ref": "#/definitions/repository.Category"
                            }
                        }
                    }
                }
            }
        },
        "/categories/{id}": {
            "get": {
                "security": [
                    {
                        "BearerAuth": []
                    }
                ],
                "description": "Get category details by ID",
                "produces": [
                    "application/json"
                ],
                "tags": [
                    "categories"
                ],
                "summary": "Get category by ID",
                "parameters": [
                    {
                        "type": "integer",
                        "description": "Category ID",
                        "name": "id",
                        "in": "path",
                        "required": true
                    }
                ],
                "responses": {
                    "200": {
                        "description": "OK",
                        "schema": {
                            "$ref": "#/definitions/repository.Category"
                        }
                    }
                }
            }
        },
        "/categories/{id}/foods": {
            "get": {
                "security": [
                    {
                        "BearerAuth": []
                    }
                ],
                "description": "Get list of foods in a category",
                "produces": [
                    "application/json"
                ],
                "tags": [
                    "categories"
                ],
                "summary": "Get foods by category",
                "parameters": [
                    {
                        "type": "integer",
                        "description": "Category ID",
                        "name": "id",
                        "in": "path",
                        "required": true
                    }
                ],
                "responses": {
                    "200": {
                        "description": "OK",
                        "schema": {
                            "type": "array",
                            "items": {
                                "$ref": "#/definitions/repository.Food"
                            }
                        }
                    }
                }
            }
        },
        "/confirm": {
            "post": {
                "description": "Confirm user registration with code",
                "consumes": [
                    "application/json"
                ],
                "produces": [
                    "application/json"
                ],
                "tags": [
                    "auth"
                ],
                "summary": "Confirm user registration",
                "parameters": [
                    {
                        "description": "Confirmation request",
                        "name": "request",
                        "in": "body",
                        "required": true,
                        "schema": {
                            "$ref": "#/definitions/handlers.ConfirmRequest"
                        }
                    }
                ],
                "responses": {
                    "200": {
                        "description": "OK",
                        "schema": {
                            "type": "object",
                            "additionalProperties": true
                        }
                    }
                }
            }
        },
        "/forgot-password": {
            "post": {
                "description": "Request password reset",
                "consumes": [
                    "application/json"
                ],
                "produces": [
                    "application/json"
                ],
                "tags": [
                    "auth"
                ],
                "summary": "Forgot password",
                "parameters": [
                    {
                        "description": "Forgot password request",
                        "name": "request",
                        "in": "body",
                        "required": true,
                        "schema": {
                            "$ref": "#/definitions/handlers.ForgotPasswordRequest"
                        }
                    }
                ],
                "responses": {
                    "200": {
                        "description": "OK",
                        "schema": {
                            "type": "object",
                            "additionalProperties": true
                        }
                    }
                }
            }
        },
        "/login": {
            "post": {
                "description": "Login with email and password",
                "consumes": [
                    "application/json"
                ],
                "produces": [
                    "application/json"
                ],
                "tags": [
                    "auth"
                ],
                "summary": "User login",
                "parameters": [
                    {
                        "description": "Login credentials",
                        "name": "request",
                        "in": "body",
                        "required": true,
                        "schema": {
                            "$ref": "#/definitions/handlers.LoginRequest"
                        }
                    }
                ],
                "responses": {
                    "200": {
                        "description": "OK",
                        "schema": {
                            "type": "object",
                            "additionalProperties": true
                        }
                    }
                }
            }
        },
        "/logout": {
            "post": {
                "security": [
                    {
                        "BearerAuth": []
                    }
                ],
                "description": "Logout user and invalidate token",
                "tags": [
                    "auth"
                ],
                "summary": "User logout",
                "responses": {
                    "200": {
                        "description": "OK",
                        "schema": {
                            "type": "object",
                            "additionalProperties": true
                        }
                    }
                }
            }
        },
        "/orders": {
            "post": {
                "security": [
                    {
                        "BearerAuth": []
                    }
                ],
                "description": "Create a new food order",
                "consumes": [
                    "application/json"
                ],
                "produces": [
                    "application/json"
                ],
                "tags": [
                    "orders"
                ],
                "summary": "Create new order",
                "parameters": [
                    {
                        "description": "Order details",
                        "name": "order",
                        "in": "body",
                        "required": true,
                        "schema": {
                            "$ref": "#/definitions/handlers.CreateOrderInput"
                        }
                    }
                ],
                "responses": {
                    "200": {
                        "description": "OK",
                        "schema": {
                            "type": "object",
                            "additionalProperties": true
                        }
                    }
                }
            }
        },
        "/orders/active": {
            "get": {
                "security": [
                    {
                        "BearerAuth": []
                    }
                ],
                "description": "Get list of orders by status (active, completed, all)",
                "produces": [
                    "application/json"
                ],
                "tags": [
                    "orders"
                ],
                "summary": "Get orders by status",
                "parameters": [
                    {
                        "type": "string",
                        "description": "Order status (active, completed, all)",
                        "name": "status",
                        "in": "query"
                    }
                ],
                "responses": {
                    "200": {
                        "description": "OK",
                        "schema": {
                            "type": "array",
                            "items": {
                                "$ref": "#/definitions/repository.Order"
                            }
                        }
                    }
                }
            }
        },
        "/orders/all": {
            "get": {
                "security": [
                    {
                        "BearerAuth": []
                    }
                ],
                "description": "Get list of orders by status (active, completed, all)",
                "produces": [
                    "application/json"
                ],
                "tags": [
                    "orders"
                ],
                "summary": "Get orders by status",
                "parameters": [
                    {
                        "type": "string",
                        "description": "Order status (active, completed, all)",
                        "name": "status",
                        "in": "query"
                    }
                ],
                "responses": {
                    "200": {
                        "description": "OK",
                        "schema": {
                            "type": "array",
                            "items": {
                                "$ref": "#/definitions/repository.Order"
                            }
                        }
                    }
                }
            }
        },
        "/orders/completed": {
            "get": {
                "security": [
                    {
                        "BearerAuth": []
                    }
                ],
                "description": "Get list of orders by status (active, completed, all)",
                "produces": [
                    "application/json"
                ],
                "tags": [
                    "orders"
                ],
                "summary": "Get orders by status",
                "parameters": [
                    {
                        "type": "string",
                        "description": "Order status (active, completed, all)",
                        "name": "status",
                        "in": "query"
                    }
                ],
                "responses": {
                    "200": {
                        "description": "OK",
                        "schema": {
                            "type": "array",
                            "items": {
                                "$ref": "#/definitions/repository.Order"
                            }
                        }
                    }
                }
            }
        },
        "/orders/{order_id}": {
            "put": {
                "security": [
                    {
                        "BearerAuth": []
                    }
                ],
                "description": "Cancel an existing order",
                "produces": [
                    "application/json"
                ],
                "tags": [
                    "orders"
                ],
                "summary": "Cancel order",
                "parameters": [
                    {
                        "type": "integer",
                        "description": "Order ID",
                        "name": "order_id",
                        "in": "path",
                        "required": true
                    }
                ],
                "responses": {
                    "200": {
                        "description": "OK",
                        "schema": {
                            "type": "object",
                            "additionalProperties": true
                        }
                    }
                }
            }
        },
        "/register": {
            "post": {
                "description": "Register a new user with email and password",
                "consumes": [
                    "application/json"
                ],
                "produces": [
                    "application/json"
                ],
                "tags": [
                    "auth"
                ],
                "summary": "Register a new user",
                "parameters": [
                    {
                        "description": "User registration info",
                        "name": "user",
                        "in": "body",
                        "required": true,
                        "schema": {
                            "$ref": "#/definitions/handlers.RegisterRequest"
                        }
                    }
                ],
                "responses": {
                    "200": {
                        "description": "OK",
                        "schema": {
                            "type": "object",
                            "additionalProperties": true
                        }
                    }
                }
            }
        },
        "/resend-code": {
            "post": {
                "description": "Resend confirmation code to user's email",
                "consumes": [
                    "application/json"
                ],
                "produces": [
                    "application/json"
                ],
                "tags": [
                    "auth"
                ],
                "summary": "Resend confirmation code",
                "parameters": [
                    {
                        "description": "Resend code request",
                        "name": "request",
                        "in": "body",
                        "required": true,
                        "schema": {
                            "$ref": "#/definitions/handlers.ResendCodeRequest"
                        }
                    }
                ],
                "responses": {
                    "200": {
                        "description": "OK",
                        "schema": {
                            "type": "object",
                            "additionalProperties": true
                        }
                    }
                }
            }
        },
        "/reset-password": {
            "post": {
                "description": "Reset password with code",
                "consumes": [
                    "application/json"
                ],
                "produces": [
                    "application/json"
                ],
                "tags": [
                    "auth"
                ],
                "summary": "Reset password",
                "parameters": [
                    {
                        "description": "Reset password request",
                        "name": "request",
                        "in": "body",
                        "required": true,
                        "schema": {
                            "$ref": "#/definitions/handlers.ResetPasswordRequest"
                        }
                    }
                ],
                "responses": {
                    "200": {
                        "description": "OK",
                        "schema": {
                            "type": "object",
                            "additionalProperties": true
                        }
                    }
                }
            }
        }
    },
    "definitions": {
        "handlers.ConfirmRequest": {
            "type": "object",
            "properties": {
                "code": {
                    "type": "integer"
                }
            }
        },
        "handlers.CreateOrderInput": {
            "type": "object",
            "properties": {
                "items": {
                    "type": "array",
                    "items": {
                        "$ref": "#/definitions/repository.OrderDetail"
                    }
                }
            }
        },
        "handlers.ForgotPasswordRequest": {
            "type": "object",
            "properties": {
                "email": {
                    "type": "string"
                }
            }
        },
        "handlers.LoginRequest": {
            "type": "object",
            "properties": {
                "email": {
                    "type": "string"
                },
                "password": {
                    "type": "string"
                }
            }
        },
        "handlers.RegisterRequest": {
            "type": "object",
            "properties": {
                "email": {
                    "type": "string"
                },
                "password": {
                    "type": "string"
                }
            }
        },
        "handlers.ResendCodeRequest": {
            "type": "object",
            "properties": {
                "email": {
                    "type": "string"
                }
            }
        },
        "handlers.ResetPasswordRequest": {
            "type": "object",
            "properties": {
                "email": {
                    "type": "string"
                },
                "password": {
                    "type": "string"
                }
            }
        },
        "repository.Category": {
            "type": "object",
            "properties": {
                "id": {
                    "type": "integer"
                },
                "name": {
                    "type": "string"
                }
            }
        },
        "repository.Food": {
            "type": "object",
            "properties": {
                "category_id": {
                    "type": "integer"
                },
                "count_food": {
                    "type": "integer"
                },
                "id": {
                    "type": "integer"
                },
                "img_url": {
                    "type": "string"
                },
                "name": {
                    "type": "string"
                },
                "price": {
                    "type": "number"
                }
            }
        },
        "repository.Order": {
            "type": "object",
            "properties": {
                "created_at": {
                    "type": "string"
                },
                "delivered_at": {
                    "type": "string"
                },
                "id": {
                    "type": "integer"
                },
                "status": {
                    "type": "string"
                },
                "total_price": {
                    "type": "number"
                },
                "user_id": {
                    "type": "integer"
                }
            }
        },
        "repository.OrderDetail": {
            "type": "object",
            "properties": {
                "count": {
                    "type": "integer"
                },
                "food_id": {
                    "type": "integer"
                }
            }
        }
    },
    "securityDefinitions": {
        "BearerAuth": {
            "description": "Type \"Bearer\" followed by a space and JWT token.",
            "type": "apiKey",
            "name": "Authorization",
            "in": "header"
        }
    }
}